setup.py
Hinagiku.egg-info/PKG-INFO
Hinagiku.egg-info/SOURCES.txt
Hinagiku.egg-info/dependency_links.txt
Hinagiku.egg-info/not-zip-safe
Hinagiku.egg-info/requires.txt
Hinagiku.egg-info/top_level.txt
hinagiku/__init__.py
hinagiku/core.py
scripts/hinagiku
