Metadata-Version: 1.0
Name: Hinagiku
Version: 0.0.0
Summary: Web page update checker
Home-page: http://hinagiku.overknee.org/
Author: Yamagishi Kazutoshi
Author-email: nysox@nysox.jp
License: MIT
Platform: any
